setup.cfg
setup.py
pump_client.egg-info/PKG-INFO
pump_client.egg-info/SOURCES.txt
pump_client.egg-info/dependency_links.txt
pump_client.egg-info/not-zip-safe
pump_client.egg-info/requires.txt
pump_client.egg-info/top_level.txt
pypump/__init__.py
pypump/client.py
pypump/compat.py
pypump/dsl.py
pypump/exceptions.py
pypump/result.py
pypump/schema.py
pypump/tor.py
pypump/utils.py