Metadata-Version: 1.0
Name: pump-client
Version: 0.5.2
Summary: Python SDK for pump APIs
Home-page: https://bitbucket.org/yimian/pump-client
Author: Yangliang Li
Author-email: liyangliang@yimian.com.cn
License: UNKNOWN
Platform: UNKNOWN
